pso_optimizer/PSO.py
pso_optimizer/__init__.py
pso_optimizer/utils.py
pswarm-0.1.1.dist-info/licenses/LICENSE
pswarm-0.1.1.dist-info/METADATA
pswarm-0.1.1.dist-info/WHEEL
pswarm-0.1.1.dist-info/top_level.txt
pswarm-0.1.1.dist-info/RECORD
