Metadata-Version: 2.4
Name: pswarm
Version: 0.1.1
Summary: A particle swarm optimization implementation
Home-page: https://github.com/riddickkakati/pswarm
Author: Riddick Kakati
Author-email: riddick.kakati93@gmail.com
Classifier: Programming Language :: Python :: 3
Classifier: License :: OSI Approved :: MIT License
Classifier: Operating System :: OS Independent
Classifier: Topic :: Scientific/Engineering :: Mathematics
Classifier: Topic :: Scientific/Engineering :: Artificial Intelligence
Requires-Python: >=3.6
License-File: LICENSE
Requires-Dist: numpy>=1.17.0
Requires-Dist: matplotlib>=3.1.0
Requires-Dist: pyyaml>=5.1.0
Dynamic: author
Dynamic: author-email
Dynamic: classifier
Dynamic: description
Dynamic: description-content-type
Dynamic: home-page
Dynamic: license-file
Dynamic: requires-dist
Dynamic: requires-python
Dynamic: summary
